a_calver_test/__init__.py
a_calver_test-2021.2.3.19.23.dist-info/METADATA
a_calver_test-2021.2.3.19.23.dist-info/WHEEL
a_calver_test-2021.2.3.19.23.dist-info/top_level.txt
a_calver_test-2021.2.3.19.23.dist-info/RECORD
