Metadata-Version: 2.1
Name: a-calver-test
Version: 2021.2.3.19.23
Summary: A CalVer demo
Home-page: https://github.com/AstraLuma/a-calver-test
Author: Jamie Bliss
Author-email: jamie@ivyleav.es
License: UNKNOWN
Platform: UNKNOWN
